taxonopy/__init__.py
taxonopy/__main__.py
taxonopy/cache_manager.py
taxonopy/cli.py
taxonopy/config.py
taxonopy/constants.py
taxonopy/entry_grouper.py
taxonopy/input_parser.py
taxonopy/logging_config.py
taxonopy/output_manager.py
taxonopy/resolve_common_names.py
taxonopy/stats_collector.py
taxonopy/query/__init__.py
taxonopy/query/executor.py
taxonopy/query/gnverifier_client.py
taxonopy/query/planner.py
taxonopy/resolution/__init__.py
taxonopy/resolution/attempt_manager.py
taxonopy/resolution/config.py
taxonopy/resolution/post_processing_for_failed.py
taxonopy/resolution/strategy/__init__.py
taxonopy/resolution/strategy/base.py
taxonopy/resolution/strategy/manager.py
taxonopy/resolution/strategy/profiles/__init__.py
taxonopy/resolution/strategy/profiles/empty_input_taxonomy.py
taxonopy/resolution/strategy/profiles/exact_match_primary_source_accepted.py
taxonopy/resolution/strategy/profiles/exact_match_primary_source_accepted_among_synonyms_simple.py
taxonopy/resolution/strategy/profiles/exact_match_primary_source_accepted_author_disambiguation.py
taxonopy/resolution/strategy/profiles/exact_match_primary_source_accepted_inner_rank_disambiguation.py
taxonopy/resolution/strategy/profiles/exact_match_primary_source_accepted_inner_rank_missing_in_result.py
taxonopy/resolution/strategy/profiles/exact_match_primary_source_accepted_multi_result_disambiguation.py
taxonopy/resolution/strategy/profiles/exact_match_primary_source_accepted_rank_level_disambiguation.py
taxonopy/resolution/strategy/profiles/exact_match_primary_source_accepted_result_within_query.py
taxonopy/resolution/strategy/profiles/exact_match_primary_source_accepted_retry.py
taxonopy/resolution/strategy/profiles/exact_match_primary_source_accepted_simple.py
taxonopy/resolution/strategy/profiles/exact_match_primary_source_accepted_synonym_disambiguation.py
taxonopy/resolution/strategy/profiles/exact_match_primary_source_multi_accepted.py
taxonopy-0.1.0b0.dist-info/METADATA
taxonopy-0.1.0b0.dist-info/WHEEL
taxonopy-0.1.0b0.dist-info/entry_points.txt
taxonopy-0.1.0b0.dist-info/licenses/LICENSE
taxonopy-0.1.0b0.dist-info/RECORD
