Metadata-Version: 2.4
Name: taxonopy
Version: 0.1.0b0
Summary: A Python package for resolving taxonomic hierarchies using the Global Names Verifier API.
Project-URL: Documentation, https://github.com/Imageomics/TaxonoPy
Project-URL: Issues, https://github.com/Imageomics/TaxonoPy/issues
Project-URL: Source, https://github.com/Imageomics/TaxonoPy
Author-email: "Matthew J. Thompson" <thompson.m.j@outlook.com>
License: MIT License
License-File: LICENSE
Keywords: alignment,hierarchy,imageomics,taxonomic-resolution,taxonomy,tree-of-life
Classifier: Development Status :: 4 - Beta
Classifier: License :: OSI Approved :: MIT License
Classifier: Operating System :: OS Independent
Classifier: Programming Language :: Python
Classifier: Programming Language :: Python :: 3.10
Classifier: Programming Language :: Python :: 3.11
Classifier: Programming Language :: Python :: 3.12
Classifier: Programming Language :: Python :: 3.13
Requires-Python: >=3.10
Requires-Dist: pandas
Requires-Dist: polars
Requires-Dist: pyarrow
Requires-Dist: pydantic
Requires-Dist: requests
Requires-Dist: tqdm
Provides-Extra: dev
Requires-Dist: datamodel-code-generator; extra == 'dev'
Requires-Dist: pre-commit; extra == 'dev'
Requires-Dist: pytest; extra == 'dev'
Requires-Dist: ruff; extra == 'dev'
Provides-Extra: nb
Requires-Dist: ipykernel; extra == 'nb'
Requires-Dist: jupyterlab; extra == 'nb'
Requires-Dist: marimo[recommended]; extra == 'nb'
